pgdtools/__init__.py
pgdtools/classify.py
pgdtools/pgdtools.py
pgdtools/data/__init__.py
pgdtools/db/__init__.py
pgdtools/db/config.py
pgdtools/db/management.py
pgdtools/db/setup_local.py
pgdtools/maintainer/__init__.py
pgdtools/maintainer/excel_tools.py
pgdtools/sub_tools/__init__.py
pgdtools/sub_tools/data.py
pgdtools/sub_tools/filters.py
pgdtools/sub_tools/format.py
pgdtools/sub_tools/headers.py
pgdtools/sub_tools/info.py
pgdtools/sub_tools/references.py
pgdtools/sub_tools/techniques.py
pgdtools/sub_tools/utilities.py
pgdtools-0.2.0.dist-info/METADATA
pgdtools-0.2.0.dist-info/WHEEL
pgdtools-0.2.0.dist-info/licenses/LICENSE
pgdtools-0.2.0.dist-info/RECORD
