Metadata-Version: 2.4
Name: pgdtools
Version: 0.2.0
Summary: Read and interact with the presolar grain database with python.
Project-URL: Source, https://github.com/galactic-forensics/pgdtools
Project-URL: Documentation, https://pgdtools.readthedocs.io
Author-email: Reto Trappitsch <reto@galactic-forensics.space>
License: MIT
License-File: LICENSE
Requires-Python: >=3.9
Requires-Dist: iniabu>=1.1.2
Requires-Dist: matplotlib>=3.7.4
Requires-Dist: numpy>=1.26.4
Requires-Dist: pandas>=2.2.0
Requires-Dist: requests>=2.31.0
Requires-Dist: scipy>=1.12.0
Provides-Extra: docs
Requires-Dist: ceresfit>=0.3.1; extra == 'docs'
Requires-Dist: mkdocs-jupyter>=0.24.8; extra == 'docs'
Requires-Dist: mkdocs-material>=9.5.25; extra == 'docs'
Requires-Dist: mkdocs>=1.6.0; extra == 'docs'
Requires-Dist: mkdocstrings[python]>=0.25.1; extra == 'docs'
Requires-Dist: notebook>=7.2.1; extra == 'docs'
Provides-Extra: maintainer
Requires-Dist: bibtexparser>=1.4.1; extra == 'maintainer'
Requires-Dist: openpyxl>=3.1.2; extra == 'maintainer'
